waafipay/__init__.py
waafipay/client.py
waafipay-0.0.9.dist-info/LICENSE
waafipay-0.0.9.dist-info/METADATA
waafipay-0.0.9.dist-info/WHEEL
waafipay-0.0.9.dist-info/top_level.txt
waafipay-0.0.9.dist-info/RECORD
