Metadata-Version: 2.1
Name: waafipay
Version: 0.0.9
Summary: A Python client for the WaafiPay API
Author: Badrudin Mohamed Ali
Author-email: badrudin.dev@gmail.com
Classifier: Programming Language :: Python :: 3
Classifier: License :: OSI Approved :: MIT License
Classifier: Operating System :: OS Independent
License-File: LICENSE
Requires-Dist: requests
